ros_rosidl_default_runtime-1.7.1.data/data/share/ament_index/resource_index/package_run_dependencies/rosidl_default_runtime
ros_rosidl_default_runtime-1.7.1.data/data/share/ament_index/resource_index/packages/rosidl_default_runtime
ros_rosidl_default_runtime-1.7.1.data/data/share/ament_index/resource_index/parent_prefix_path/rosidl_default_runtime
ros_rosidl_default_runtime-1.7.1.data/data/share/rosidl_default_runtime/local_setup.bash
ros_rosidl_default_runtime-1.7.1.data/data/share/rosidl_default_runtime/local_setup.dsv
ros_rosidl_default_runtime-1.7.1.data/data/share/rosidl_default_runtime/local_setup.sh
ros_rosidl_default_runtime-1.7.1.data/data/share/rosidl_default_runtime/local_setup.zsh
ros_rosidl_default_runtime-1.7.1.data/data/share/rosidl_default_runtime/package.dsv
ros_rosidl_default_runtime-1.7.1.data/data/share/rosidl_default_runtime/package.xml
ros_rosidl_default_runtime-1.7.1.data/data/share/rosidl_default_runtime/cmake/ament_cmake_export_dependencies-extras.cmake
ros_rosidl_default_runtime-1.7.1.data/data/share/rosidl_default_runtime/cmake/rosidl_default_runtimeConfig-version.cmake
ros_rosidl_default_runtime-1.7.1.data/data/share/rosidl_default_runtime/cmake/rosidl_default_runtimeConfig.cmake
ros_rosidl_default_runtime-1.7.1.data/data/share/rosidl_default_runtime/environment/ament_prefix_path.dsv
ros_rosidl_default_runtime-1.7.1.data/data/share/rosidl_default_runtime/environment/ament_prefix_path.sh
ros_rosidl_default_runtime-1.7.1.data/data/share/rosidl_default_runtime/environment/path.dsv
ros_rosidl_default_runtime-1.7.1.data/data/share/rosidl_default_runtime/environment/path.sh
rosidl_default_runtime/_dummy.cpython-310-x86_64-linux-gnu.so
ros_rosidl_default_runtime-1.7.1.dist-info/METADATA
ros_rosidl_default_runtime-1.7.1.dist-info/WHEEL
ros_rosidl_default_runtime-1.7.1.dist-info/top_level.txt
ros_rosidl_default_runtime-1.7.1.dist-info/RECORD
