Metadata-Version: 2.4
Name: ros-rosidl-default-runtime
Version: 1.7.1
Summary: A ROS package that aggregates and manages runtime dependencies for rosidl packages, simplifying development and reducing boilerplate.
Requires-Dist: ros-action-msgs~=2.3.0
Requires-Dist: ros-service-msgs~=2.3.0
Requires-Dist: ros-rosidl-core-runtime~=0.3.1
Dynamic: description
Dynamic: description-content-type
Dynamic: requires-dist
Dynamic: summary
